{
  "ottilie-solitaire-50078-e": {
    "settingHeight": "High Set",
    "bandType": "Accents",
    "settingType": "Solitaire"
  },
  "kalliope-solitaire-50009-e": {
    "settingHeight": "High Set",
    "bandType": "Accents",
    "settingType": "Solitaire"
  },
  "gemma-solitaire-81647": {
    "settingHeight": "High Set",
    "bandType": "Accents",
    "settingType": "Solitaire"
  },
  "elodie-solitaire-85346": {
    "settingHeight": "High Set",
    "bandType": "Accents",
    "settingType": "Solitaire"
  },
  "zaria-three-stone-50229-e": {
    "settingHeight": "High Set",
    "bandType": "Accents",
    "settingType": "Solitaire"
  },
  "zarina-engagement-51114-e": {
    "settingHeight": "High Set",
    "bandType": "Accents",
    "settingType": "Solitaire"
  },
  "liesel-solitaire-50025-e": {
    "settingHeight": "High Set",
    "bandType": "Accents",
    "settingType": "Solitaire"
  },
  "ulyana-cathedral-85147": {
    "settingHeight": "High Set",
    "bandType": "Accents",
    "settingType": "Solitaire"
  },
  "drusilla-baguette-remount-50299-e": {
    "settingHeight": "High Set",
    "bandType": "Accents",
    "settingType": "Solitaire"
  },
  "yelena-bypass-50214-e": {
    "settingHeight": "High Set",
    "bandType": "Accents",
    "settingType": "Solitaire"
  },
  "primrose-bypass-50085-e": {
    "settingHeight": "High Set",
    "bandType": "Accents",
    "settingType": "Solitaire"
  },
  "noor-solitaire-85264-1": {
    "settingHeight": "High Set",
    "bandType": "Accents",
    "settingType": "Solitaire"
  },
  "xela-engagement-51217-e": {
    "settingHeight": "High Set",
    "bandType": "Accents",
    "settingType": "Solitaire"
  },
  "yana-engagement-51218-e": {
    "settingHeight": "High Set",
    "bandType": "Accents",
    "settingType": "Solitaire"
  },
  "pearl-engagement-85280": {
    "settingHeight": "High Set",
    "bandType": "Accents",
    "settingType": "Solitaire"
  },
  "tamsin-channel-set-50152-e": {
    "settingHeight": "High Set",
    "bandType": "Accents",
    "settingType": "Solitaire"
  },
  "freya-color-81330-6x4": {
    "settingHeight": "High Set",
    "bandType": "Accents",
    "settingType": "Solitaire"
  },
  "wilhelmina-bypass-50192-e": {
    "settingHeight": "High Set",
    "bandType": "Accents",
    "settingType": "Solitaire"
  },
  "pia-engagement-51169-e": {
    "settingHeight": "High Set",
    "bandType": "Accents",
    "settingType": "Solitaire"
  },
  "adeline-solitaire-85164-5x3": {
    "settingHeight": "High Set",
    "bandType": "Plain",
    "settingType": "Solitaire"
  },
  "quincy-solitaire-85288-1": {
    "settingHeight": "High Set",
    "bandType": "Plain",
    "settingType": "Solitaire"
  },
  "tira-remount-51192-e": {
    "settingHeight": "High Set",
    "bandType": "Plain",
    "settingType": "Solitaire"
  },
  "isolde-channel-set-50001-e": {
    "settingHeight": "High Set",
    "bandType": "Plain",
    "settingType": "Solitaire"
  },
  "saskia-bypass-50139-e": {
    "settingHeight": "High Set",
    "bandType": "Plain",
    "settingType": "Pavé"
  },
  "yvette-solitaire-84376": {
    "settingHeight": "High Set",
    "bandType": "Plain",
    "settingType": "Pavé"
  },
  "hadley-solitaire-85254-1": {
    "settingHeight": "High Set",
    "bandType": "Plain",
    "settingType": "Pavé"
  },
  "klara-solitaire-85258-1": {
    "settingHeight": "High Set",
    "bandType": "Plain",
    "settingType": "Pavé"
  },
  "vega-baguette-remount-84358": {
    "settingHeight": "High Set",
    "bandType": "Plain",
    "settingType": "Pavé"
  },
  "juno-solitaire-81990": {
    "settingHeight": "High Set",
    "bandType": "Plain",
    "settingType": "Pavé"
  },
  "ilse-engagement-51158-e-4-5": {
    "settingHeight": "High Set",
    "bandType": "Plain",
    "settingType": "Pavé"
  },
  "vesper-solitaire-51090-e-4": {
    "settingHeight": "High Set",
    "bandType": "Plain",
    "settingType": "Pavé"
  },
  "zephyrine-solitaire-85162-1": {
    "settingHeight": "High Set",
    "bandType": "Plain",
    "settingType": "Pavé"
  },
  "tatiana-solitaire-85293-1": {
    "settingHeight": "High Set",
    "bandType": "Plain",
    "settingType": "Pavé"
  },
  "astrid-cluster-50240-e": {
    "settingHeight": "High Set",
    "bandType": "Plain",
    "settingType": "Pavé"
  },
  "jeneva-baguette-remount-50405-e": {
    "settingHeight": "High Set",
    "bandType": "Plain",
    "settingType": "Pavé"
  },
  "magnolia-channel-set-50026-e": {
    "settingHeight": "High Set",
    "bandType": "Plain",
    "settingType": "Pavé"
  },
  "stella-solitaire-83164": {
    "settingHeight": "High Set",
    "bandType": "Plain",
    "settingType": "Pavé"
  },
  "jora-engagement-50964-e": {
    "settingHeight": "High Set",
    "bandType": "Plain",
    "settingType": "Pavé"
  },
  "romy-cathedral-85133": {
    "settingHeight": "High Set",
    "bandType": "Plain",
    "settingType": "Pavé"
  },
  "coralie-baguette-remount-50873-e": {
    "settingHeight": "High Set",
    "bandType": "Plain",
    "settingType": "Pavé"
  },
  "quenby-engagement-51172-e-1": {
    "settingHeight": "High Set",
    "bandType": "Plain",
    "settingType": "Pavé"
  },
  "eloise-solitaire-81206": {
    "settingHeight": "High Set",
    "bandType": "Plain",
    "settingType": "Pavé"
  },
  "lavinia-engagement-85260-1": {
    "settingHeight": "High Set",
    "bandType": "Plain",
    "settingType": "Pavé"
  },
  "tova-solitaire-51073-e-1": {
    "settingHeight": "High Set",
    "bandType": "Plain",
    "settingType": "Pavé"
  },
  "seraphina-solitaire-84303": {
    "settingHeight": "High Set",
    "bandType": "Plain",
    "settingType": "Pavé"
  },
  "brielle-cluster-50292-e": {
    "settingHeight": "High Set",
    "bandType": "Plain",
    "settingType": "Pavé"
  },
  "amelie-solitaire-85325-1": {
    "settingHeight": "High Set",
    "bandType": "Plain",
    "settingType": "Pavé"
  },
  "ophira-engagement-51168-e": {
    "settingHeight": "High Set",
    "bandType": "Plain",
    "settingType": "Pavé"
  },
  "una-solitaire-51089-e-1": {
    "settingHeight": "High Set",
    "bandType": "Plain",
    "settingType": "Bezel"
  },
  "esme-baguette-remount-83856": {
    "settingHeight": "High Set",
    "bandType": "Plain",
    "settingType": "Bezel"
  },
  "estelle-fashion-85185-6x4": {
    "settingHeight": "High Set",
    "bandType": "Plain",
    "settingType": "Bezel"
  },
  "iris-baguette-remount-81885-1": {
    "settingHeight": "High Set",
    "bandType": "Plain",
    "settingType": "Bezel"
  },
  "cosette-solitaire-85333-1": {
    "settingHeight": "High Set",
    "bandType": "Twisted",
    "settingType": "Bezel"
  },
  "faina-twisted-shank-51144-e-1": {
    "settingHeight": "High Set",
    "bandType": "Twisted",
    "settingType": "Bezel"
  },
  "romilly-bypass-50097-e": {
    "settingHeight": "High Set",
    "bandType": "Twisted",
    "settingType": "Bezel"
  },
  "lara-three-stone-82571-a": {
    "settingHeight": "High Set",
    "bandType": "Twisted",
    "settingType": "Bezel"
  },
  "odessa-bypass-84287": {
    "settingHeight": "High Set",
    "bandType": "Twisted",
    "settingType": "Bezel"
  },
  "briony-solitaire-85332-3-8": {
    "settingHeight": "High Set",
    "bandType": "Twisted",
    "settingType": "Bezel"
  },
  "ursa-solitaire-84355-1": {
    "settingHeight": "High Set",
    "bandType": "Twisted",
    "settingType": "Bezel"
  },
  "greta-engagement-51155-e": {
    "settingHeight": "High Set",
    "bandType": "Twisted",
    "settingType": "Bezel"
  },
  "jolie-engagement-84881": {
    "settingHeight": "High Set",
    "bandType": "Twisted",
    "settingType": "Bezel"
  },
  "hollis-prong-set-50353-e-1": {
    "settingHeight": "High Set",
    "bandType": "Twisted",
    "settingType": "Bezel"
  },
  "quintessa-bypass-50088-e": {
    "settingHeight": "High Set",
    "bandType": "Twisted",
    "settingType": "Toi Et Moi"
  },
  "greer-prong-set-50322-e": {
    "settingHeight": "High Set",
    "bandType": "Twisted",
    "settingType": "Toi Et Moi"
  },
  "ursela-remount-50635-e-035": {
    "settingHeight": "High Set",
    "bandType": "Twisted",
    "settingType": "Toi Et Moi"
  },
  "greta-engagement-85242-1": {
    "settingHeight": "High Set",
    "bandType": "Twisted",
    "settingType": "Toi Et Moi"
  },
  "jessamine-engagement-85257-5x3": {
    "settingHeight": "High Set",
    "bandType": "Twisted",
    "settingType": "Toi Et Moi"
  },
  "chloe-three-stone-80767": {
    "settingHeight": "High Set",
    "bandType": "Twisted",
    "settingType": "Toi Et Moi"
  },
  "sela-remount-51182-e": {
    "settingHeight": "High Set",
    "bandType": "Twisted",
    "settingType": "Toi Et Moi"
  },
  "opal-three-stone-82844-a": {
    "settingHeight": "High Set",
    "bandType": "Twisted",
    "settingType": "Toi Et Moi"
  },
  "arai-prong-set-50804-e": {
    "settingHeight": "High Set",
    "bandType": "Twisted",
    "settingType": "Toi Et Moi"
  },
  "zinnia-cluster-84476": {
    "settingHeight": "High Set",
    "bandType": "Twisted",
    "settingType": "Toi Et Moi"
  },
  "marigold-engagement-85261": {
    "settingHeight": "High Set",
    "bandType": "Twisted",
    "settingType": "Toi Et Moi"
  },
  "yasmin-solitaire-85305-10-5x7": {
    "settingHeight": "High Set",
    "bandType": "Twisted",
    "settingType": "Toi Et Moi"
  },
  "zelda-solitaire-85324-1": {
    "settingHeight": "High Set",
    "bandType": "Twisted",
    "settingType": "Toi Et Moi"
  },
  "demi-solitaire-85345-10-5x7-5": {
    "settingHeight": "High Set",
    "bandType": "Twisted",
    "settingType": "Toi Et Moi"
  },
  "oriana-engagement-85278": {
    "settingHeight": "High Set",
    "bandType": "Twisted",
    "settingType": "Toi Et Moi"
  },
  "clio-remount-84757": {
    "settingHeight": "High Set",
    "bandType": "Plain",
    "settingType": "Toi Et Moi"
  },
  "xanthe-solitaire-85157-1": {
    "settingHeight": "High Set",
    "bandType": "Plain",
    "settingType": "Toi Et Moi"
  },
  "xara-engagement-50204-e": {
    "settingHeight": "High Set",
    "bandType": "Plain",
    "settingType": "Toi Et Moi"
  },
  "ula-engagement-51206-e-5x3": {
    "settingHeight": "High Set",
    "bandType": "Plain",
    "settingType": "Toi Et Moi"
  },
  "kira-solitaire-82022": {
    "settingHeight": "High Set",
    "bandType": "Plain",
    "settingType": "Toi Et Moi"
  },
  "juniper-bypass-50003-e": {
    "settingHeight": "High Set",
    "bandType": "Plain",
    "settingType": "Toi Et Moi"
  },
  "yara-engagement-51111-e": {
    "settingHeight": "High Set",
    "bandType": "Plain",
    "settingType": "Unique"
  },
  "ines-engagement-85255-1": {
    "settingHeight": "High Set",
    "bandType": "Plain",
    "settingType": "Unique"
  },
  "bria-twisted-shank-51120-e-1": {
    "settingHeight": "High Set",
    "bandType": "Plain",
    "settingType": "Unique"
  },
  "zora-prong-set-50791-e": {
    "settingHeight": "High Set",
    "bandType": "Plain",
    "settingType": "Unique"
  },
  "ysabel-engagement-85158-1": {
    "settingHeight": "High Set",
    "bandType": "Plain",
    "settingType": "Unique"
  },
  "dovie-engagement-51138-e-1": {
    "settingHeight": "High Set",
    "bandType": "Plain",
    "settingType": "Unique"
  },
  "mirabel-fashion-85107-5x3": {
    "settingHeight": "High Set",
    "bandType": "Plain",
    "settingType": "Unique"
  },
  "wila-hidden-halo-51210-e-13-4": {
    "settingHeight": "High Set",
    "bandType": "Plain",
    "settingType": "Unique"
  },
  "talia-vintage-84326": {
    "settingHeight": "High Set",
    "bandType": "Plain",
    "settingType": "Unique"
  },
  "nyla-prong-set-84275": {
    "settingHeight": "High Set",
    "bandType": "Plain",
    "settingType": "Unique"
  },
  "aria-prong-set-50274-e-5": {
    "settingHeight": "High Set",
    "bandType": "Plain",
    "settingType": "Unique"
  },
  "etta-prong-set-50300-e": {
    "settingHeight": "High Set",
    "bandType": "Plain",
    "settingType": "Unique"
  },
  "posy-solitaire-85131-1": {
    "settingHeight": "High Set",
    "bandType": "Plain",
    "settingType": "Unique"
  },
  "mira-baguette-remount-82754-c": {
    "settingHeight": "High Set",
    "bandType": "Plain",
    "settingType": "Unique"
  },
  "petra-bypass-84294": {
    "settingHeight": "High Set",
    "bandType": "Plain",
    "settingType": "Unique"
  },
  "halia-engagement-50957-e": {
    "settingHeight": "High Set",
    "bandType": "Plain",
    "settingType": "Unique"
  },
  "daphne-solitaire-80940": {
    "settingHeight": "High Set",
    "bandType": "Plain",
    "settingType": "Unique"
  },
  "zia-engagement-51222-e": {
    "settingHeight": "High Set",
    "bandType": "Plain",
    "settingType": "Unique"
  },
  "karla-engagement-51161-e-4-5": {
    "settingHeight": "High Set",
    "bandType": "Plain",
    "settingType": "Unique"
  },
  "nora-baguette-remount-82841": {
    "settingHeight": "High Set",
    "bandType": "Plain",
    "settingType": "Unique"
  },
  "vanya-engagement-50650-e-1": {
    "settingHeight": "High Set",
    "bandType": "Plain",
    "settingType": "Unique"
  },
  "penelope-three-stone-82876-1-2": {
    "settingHeight": "High Set",
    "bandType": "Accents",
    "settingType": "Unique"
  },
  "rea-engagement-51174-e-4-5x3": {
    "settingHeight": "High Set",
    "bandType": "Accents",
    "settingType": "Unique"
  },
  "kestrel-engagement-50975-e-1": {
    "settingHeight": "High Set",
    "bandType": "Accents",
    "settingType": "Unique"
  },
  "maren-multi-row-50486-e": {
    "settingHeight": "High Set",
    "bandType": "Accents",
    "settingType": "Unique"
  },
  "fenna-engagement-50932-e-1": {
    "settingHeight": "High Set",
    "bandType": "Accents",
    "settingType": "Unique"
  },
  "henna-engagement-85373": {
    "settingHeight": "High Set",
    "bandType": "Accents",
    "settingType": "Unique"
  },
  "jora-engagement-51160-e-1": {
    "settingHeight": "High Set",
    "bandType": "Accents",
    "settingType": "Unique"
  },
  "olwen-three-stone-50506-e": {
    "settingHeight": "High Set",
    "bandType": "Accents",
    "settingType": "Unique"
  },
  "rhea-twisted-shank-85290": {
    "settingHeight": "High Set",
    "bandType": "Accents",
    "settingType": "Unique"
  },
  "wren-three-stone-84360": {
    "settingHeight": "High Set",
    "bandType": "Accents",
    "settingType": "Unique"
  },
  "wisteria-cathedral-85153": {
    "settingHeight": "High Set",
    "bandType": "Accents",
    "settingType": "Halo"
  },
  "elke-halo-50924-e-1": {
    "settingHeight": "High Set",
    "bandType": "Accents",
    "settingType": "Halo"
  },
  "linnea-three-stone-50447-e": {
    "settingHeight": "High Set",
    "bandType": "Accents",
    "settingType": "Halo"
  },
  "solene-engagement-51057-e": {
    "settingHeight": "High Set",
    "bandType": "Accents",
    "settingType": "Halo"
  },
  "fern-three-stone-50309-e": {
    "settingHeight": "High Set",
    "bandType": "Accents",
    "settingType": "Halo"
  },
  "galena-engagement-50938-e": {
    "settingHeight": "High Set",
    "bandType": "Accents",
    "settingType": "Halo"
  },
  "ximena-engagement-85298": {
    "settingHeight": "High Set",
    "bandType": "Accents",
    "settingType": "Halo"
  },
  "hyacinth-engagement-51156-e-10-5x8": {
    "settingHeight": "High Set",
    "bandType": "Accents",
    "settingType": "Halo"
  },
  "nessa-halo-50489-e": {
    "settingHeight": "High Set",
    "bandType": "Accents",
    "settingType": "Halo"
  },
  "maia-engagement-51163-e-7-5x5-5": {
    "settingHeight": "High Set",
    "bandType": "Accents",
    "settingType": "Halo"
  },
  "zara-three-stone-83660": {
    "settingHeight": "High Set",
    "bandType": "Accents",
    "settingType": "Halo"
  },
  "liana-engagement-84961-10x5": {
    "settingHeight": "High Set",
    "bandType": "Accents",
    "settingType": "Halo"
  },
  "xanadu-prong-set-50655-e": {
    "settingHeight": "High Set",
    "bandType": "Accents",
    "settingType": "Halo"
  },
  "delphine-bypass-83852": {
    "settingHeight": "Low Set",
    "bandType": "Accents",
    "settingType": "Halo"
  },
  "undine-cluster-50154-e": {
    "settingHeight": "Low Set",
    "bandType": "Accents",
    "settingType": "Halo"
  },
  "imogen-engagement-84843-1": {
    "settingHeight": "Low Set",
    "bandType": "Accents",
    "settingType": "Halo"
  },
  "lily-engagement-51196-e-10-3x6-2": {
    "settingHeight": "Low Set",
    "bandType": "Accents",
    "settingType": "Halo"
  },
  "phaedra-multi-row-50538-e-1": {
    "settingHeight": "Low Set",
    "bandType": "Accents",
    "settingType": "Halo"
  },
  "dahlia-engagement-84763": {
    "settingHeight": "Low Set",
    "bandType": "Accents",
    "settingType": "Halo"
  },
  "danica-halo-85184-1-2": {
    "settingHeight": "Low Set",
    "bandType": "Accents",
    "settingType": "Halo"
  },
  "ula-hidden-halo-85295-5": {
    "settingHeight": "Low Set",
    "bandType": "Accents",
    "settingType": "Halo"
  },
  "calla-channel-set-50297-e": {
    "settingHeight": "Low Set",
    "bandType": "Accents",
    "settingType": "Halo"
  },
  "eira-engagement-51140-e-10x8": {
    "settingHeight": "Low Set",
    "bandType": "Accents",
    "settingType": "Halo"
  },
  "niamh-split-shank-85112": {
    "settingHeight": "Low Set",
    "bandType": "Accents",
    "settingType": "Halo"
  },
  "reverie-solitaire-84295": {
    "settingHeight": "Low Set",
    "bandType": "Accents",
    "settingType": "Halo"
  },
  "yolanda-multi-row-50774-e-1": {
    "settingHeight": "Low Set",
    "bandType": "Accents",
    "settingType": "Halo"
  },
  "devi-halo-50893-e-1": {
    "settingHeight": "Low Set",
    "bandType": "Accents",
    "settingType": "Halo"
  },
  "vada-hidden-halo-51207-e-13-4": {
    "settingHeight": "Low Set",
    "bandType": "Accents",
    "settingType": "Halo"
  },
  "sable-hidden-halo-85292-1": {
    "settingHeight": "Low Set",
    "bandType": "Accents",
    "settingType": "Halo"
  },
  "xylia-engagement-51110-e": {
    "settingHeight": "Low Set",
    "bandType": "Accents",
    "settingType": "Halo"
  },
  "indira-engagement-50960-e": {
    "settingHeight": "Low Set",
    "bandType": "Accents",
    "settingType": "Halo"
  },
  "xena-three-stone-83512": {
    "settingHeight": "Low Set",
    "bandType": "Accents",
    "settingType": "Halo"
  },
  "yara-halo-83515-5": {
    "settingHeight": "Low Set",
    "bandType": "Accents",
    "settingType": "Halo"
  },
  "elara-engagement-84765": {
    "settingHeight": "Low Set",
    "bandType": "Accents",
    "settingType": "Halo"
  },
  "liv-engagement-51162-e-11-5x8": {
    "settingHeight": "Low Set",
    "bandType": "Accents",
    "settingType": "Halo"
  },
  "violet-cluster-83249": {
    "settingHeight": "Low Set",
    "bandType": "Accents",
    "settingType": "Halo"
  },
  "nira-engagement-51165-e": {
    "settingHeight": "Low Set",
    "bandType": "Accents",
    "settingType": "Halo"
  },
  "octavia-halo-85127-1": {
    "settingHeight": "Low Set",
    "bandType": "Accents",
    "settingType": "Halo"
  },
  "luna-cluster-84269": {
    "settingHeight": "Low Set",
    "bandType": "Accents",
    "settingType": "Halo"
  },
  "bella-solitaire-80180": {
    "settingHeight": "Low Set",
    "bandType": "Accents",
    "settingType": "Halo"
  },
  "florence-engagement-85230": {
    "settingHeight": "Low Set",
    "bandType": "Accents",
    "settingType": "Halo"
  },
  "maeve-multi-row-84272": {
    "settingHeight": "Low Set",
    "bandType": "Accents",
    "settingType": "Halo"
  },
  "bryony-solitaire-84732-6x4": {
    "settingHeight": "Low Set",
    "bandType": "Accents",
    "settingType": "Halo"
  },
  "quinn-color-82900-6x4": {
    "settingHeight": "Low Set",
    "bandType": "Accents",
    "settingType": "Halo"
  },
  "verity-halo-85151": {
    "settingHeight": "Low Set",
    "bandType": "Accents",
    "settingType": "Halo"
  },
  "gaia-engagement-85370": {
    "settingHeight": "Low Set",
    "bandType": "Accents",
    "settingType": "Halo"
  },
  "winona-hidden-halo-85297-10x8": {
    "settingHeight": "Low Set",
    "bandType": "Accents",
    "settingType": "Halo"
  },
  "jade-three-stone-84124": {
    "settingHeight": "Low Set",
    "bandType": "Accents",
    "settingType": "Halo"
  },
  "shea-multi-row-50566-e-1": {
    "settingHeight": "Low Set",
    "bandType": "Accents",
    "settingType": "Halo"
  },
  "fleur-multi-row-83904": {
    "settingHeight": "Low Set",
    "bandType": "Accents",
    "settingType": "Halo"
  },
  "vienne-hidden-halo-85296-11x7-5": {
    "settingHeight": "Low Set",
    "bandType": "Accents",
    "settingType": "Halo"
  },
  "mara-engagement-50982-e": {
    "settingHeight": "Low Set",
    "bandType": "Accents",
    "settingType": "Halo"
  },
  "adira-engagement-51116-e": {
    "settingHeight": "Low Set",
    "bandType": "Accents",
    "settingType": "Halo"
  },
  "faye-engagement-84766": {
    "settingHeight": "Low Set",
    "bandType": "Accents",
    "settingType": "Halo"
  },
  "giselle-three-stone-84006": {
    "settingHeight": "Low Set",
    "bandType": "Accents",
    "settingType": "Halo"
  },
  "rosalind-multi-row-50562-e": {
    "settingHeight": "Low Set",
    "bandType": "Accents",
    "settingType": "Halo"
  },
  "kiera-engagement-84905": {
    "settingHeight": "Low Set",
    "bandType": "Accents",
    "settingType": "Halo"
  },
  "liora-engagement-50981-e-1": {
    "settingHeight": "Low Set",
    "bandType": "Accents",
    "settingType": "Halo"
  },
  "kalia-multi-row-84262": {
    "settingHeight": "Low Set",
    "bandType": "Accents",
    "settingType": "Hidden Halo"
  },
  "nima-engagement-50987-e": {
    "settingHeight": "Low Set",
    "bandType": "Accents",
    "settingType": "Hidden Halo"
  },
  "iola-multi-row-50366-e": {
    "settingHeight": "Low Set",
    "bandType": "Accents",
    "settingType": "Hidden Halo"
  },
  "anya-bypass-84584-1": {
    "settingHeight": "Low Set",
    "bandType": "Accents",
    "settingType": "Hidden Halo"
  },
  "hazel-three-stone-81785": {
    "settingHeight": "Low Set",
    "bandType": "Accents",
    "settingType": "Hidden Halo"
  },
  "halle-engagement-84832": {
    "settingHeight": "Low Set",
    "bandType": "Accents",
    "settingType": "Hidden Halo"
  },
  "rania-engagement-51048-e": {
    "settingHeight": "Low Set",
    "bandType": "Accents",
    "settingType": "Hidden Halo"
  },
  "camille-three-stone-83817": {
    "settingHeight": "Low Set",
    "bandType": "Accents",
    "settingType": "Hidden Halo"
  },
  "theodora-multi-row-50622-e": {
    "settingHeight": "Low Set",
    "bandType": "Accents",
    "settingType": "Hidden Halo"
  },
  "beatrix-three-stone-85165-1": {
    "settingHeight": "Low Set",
    "bandType": "Accents",
    "settingType": "Hidden Halo"
  },
  "farah-engagement-85368": {
    "settingHeight": "Low Set",
    "bandType": "Accents",
    "settingType": "Hidden Halo"
  },
  "willow-halo-83495-10x8": {
    "settingHeight": "Low Set",
    "bandType": "Accents",
    "settingType": "Hidden Halo"
  },
  "brynn-multi-row-50843-e-1": {
    "settingHeight": "Low Set",
    "bandType": "Accents",
    "settingType": "Hidden Halo"
  },
  "cordelia-fashion-85178-10x8": {
    "settingHeight": "Low Set",
    "bandType": "Accents",
    "settingType": "Hidden Halo"
  },
  "rosalie-three-stone-82956-1": {
    "settingHeight": "Low Set",
    "bandType": "Accents",
    "settingType": "Hidden Halo"
  },
  "celeste-solitaire-80400": {
    "settingHeight": "Low Set",
    "bandType": "Accents",
    "settingType": "Hidden Halo"
  },
  "una-solitaire-83242": {
    "settingHeight": "Low Set",
    "bandType": "Accents",
    "settingType": "Hidden Halo"
  },
  "sienna-three-stone-85134-1": {
    "settingHeight": "Low Set",
    "bandType": "Accents",
    "settingType": "Hidden Halo"
  },
  "kassia-multi-row-50427-e": {
    "settingHeight": "Low Set",
    "bandType": "Accents",
    "settingType": "Hidden Halo"
  },
  "wynne-multi-row-50652-e": {
    "settingHeight": "Low Set",
    "bandType": "Accents",
    "settingType": "Hidden Halo"
  },
  "nadia-multi-row-50059-e": {
    "settingHeight": "Low Set",
    "bandType": "Accents",
    "settingType": "Hidden Halo"
  },
  "amara-three-stone-83667-11-2": {
    "settingHeight": "Low Set",
    "bandType": "Side Stone",
    "settingType": "Hidden Halo"
  },
  "quinnley-multi-row-50560-e": {
    "settingHeight": "Low Set",
    "bandType": "Side Stone",
    "settingType": "Hidden Halo"
  },
  "hera-multi-row-84030-1": {
    "settingHeight": "Low Set",
    "bandType": "Side Stone",
    "settingType": "Hidden Halo"
  },
  "thalia-halo-85137-1": {
    "settingHeight": "Low Set",
    "bandType": "Side Stone",
    "settingType": "Hidden Halo"
  },
  "aurora-solitaire-80066": {
    "settingHeight": "Low Set",
    "bandType": "Side Stone",
    "settingType": "Hidden Halo"
  },
  "caia-engagement-51123-e": {
    "settingHeight": "Low Set",
    "bandType": "Side Stone",
    "settingType": "Hidden Halo"
  },
  "orla-multi-row-51008-e-1": {
    "settingHeight": "Low Set",
    "bandType": "Side Stone",
    "settingType": "Hidden Halo"
  },
  "xiomara-pav-84370": {
    "settingHeight": "Low Set",
    "bandType": "Side Stone",
    "settingType": "Hidden Halo"
  },
  "winter-pav-51094-e-6x4": {
    "settingHeight": "Low Set",
    "bandType": "Side Stone",
    "settingType": "Hidden Halo"
  },
  "valentina-baguette-remount-50189-e": {
    "settingHeight": "Low Set",
    "bandType": "Side Stone",
    "settingType": "Hidden Halo"
  },
  "phoebe-multi-row-51012-e-10x8": {
    "settingHeight": "Low Set",
    "bandType": "Side Stone",
    "settingType": "Hidden Halo"
  },
  "genevieve-engagement-84775": {
    "settingHeight": "Low Set",
    "bandType": "Side Stone",
    "settingType": "Hidden Halo"
  },
  "ivy-multi-row-84042": {
    "settingHeight": "Low Set",
    "bandType": "Side Stone",
    "settingType": "Hidden Halo"
  },
  "quill-engagement-51016-e-1": {
    "settingHeight": "Low Set",
    "bandType": "Side Stone",
    "settingType": "Hidden Halo"
  },
  "tess-three-stone-83232": {
    "settingHeight": "High Set",
    "bandType": "Side Stone",
    "settingType": "Hidden Halo"
  },
  "briar-three-stone-83770": {
    "settingHeight": "Low Set",
    "bandType": "Side Stone",
    "settingType": "Hidden Halo"
  }
}